{
  "users": [],
  "article": [
    {
      "id": "2cdd",
      "name": "Bestfizz",
      "checked": false
    },
    {
      "id": "95cb",
      "name": "Belvita - Petit déjeuner pépites chocolat",
      "checked": false
    },
    {
      "id": "4284",
      "name": "Belvita - Petit déjeuner pépites chocolat",
      "checked": false
    },
    {
      "id": "aed3",
      "name": "Belvita - Petit déjeuner pépites chocolat",
      "checked": false
    },
    {
      "id": "63e7",
      "name": "Belvita - Petit déjeuner pépites chocolat",
      "checked": false
    }
  ]
}
